[
  {
    "caption": "Table 3: Classification accuracy (%, higher is better) of graph convolution methods trained with BP and DFA, on citation networks [65]. But for ChebConv and DNAConv, DFA performance nearly matches BP performance. Values in bold when DFA is within 2.5% of BP.",
    "captionBoundary": {
      "x1": 107.69100189208984,
      "x2": 504.3453674316406,
      "y1": 613.091552734375,
      "y2": 640.9119873046875
    },
    "figType": "Table",
    "imageText": [
      "Cora",
      "79.2",
      "75.4",
      "80.1",
      "79.9",
      "81.0",
      "77.7",
      "82.6",
      "80.6",
      "84.6",
      "82.9",
      "CiteSeer",
      "69.5",
      "67.6",
      "71.6",
      "69.4",
      "70.0",
      "69.8",
      "72.0",
      "71.2",
      "73.4",
      "70.8",
      "PubMed",
      "79.5",
      "75.7",
      "78.8",
      "77.8",
      "77.5",
      "77.2",
      "77.7",
      "77.1",
      "87.2",
      "79.9",
      "ChebConv",
      "GraphConv",
      "SplineConv",
      "GATConv",
      "DNAConv",
      "BP",
      "DFA",
      "BP",
      "DFA",
      "BP",
      "DFA",
      "BP",
      "DFA",
      "BP",
      "DFA"
    ],
    "name": "3",
    "page": 5,
    "regionBoundary": {
      "x1": 134.88,
      "x2": 477.12,
      "y1": 653.76,
      "y2": 720.0
    },
    "renderDpi": 150,
    "renderURL": "//Users/meghamariam/PROJECTS/PROJ1_Dataset/PROJ1_Crossmodal-Traversal/DATASET/pap-seg/fig/sp_0001/sp_0001-Table3-1.png",
    "id": "sp_0001-Table3-1"
  },
  {
    "caption": "Table 4: AUC and Average Precision (AP, higher is better) for a GraphConv GAE trained with BP or DFA on citation networks. DFA reproduces BP performance.",
    "captionBoundary": {
      "x1": 132.83299255371094,
      "x2": 277.51116943359375,
      "y1": 202.39651489257812,
      "y2": 252.03497314453125
    },
    "figType": "Table",
    "imageText": [
      "Cora",
      "AUC",
      "0.918",
      "0.900",
      "AP",
      "0.918",
      "0.900",
      "CiteSeer",
      "AUC",
      "0.886",
      "0.879",
      "AP",
      "0.895",
      "0.889",
      "PubMed",
      "AUC",
      "0.967",
      "0.945",
      "AP",
      "0.966",
      "0.945",
      "GAE",
      "BP",
      "DFA"
    ],
    "name": "4",
    "page": 6,
    "regionBoundary": {
      "x1": 134.88,
      "x2": 274.08,
      "y1": 91.67999999999999,
      "y2": 191.04
    },
    "renderDpi": 150,
    "renderURL": "//Users/meghamariam/PROJECTS/PROJ1_Dataset/PROJ1_Crossmodal-Traversal/DATASET/pap-seg/fig/sp_0001/sp_0001-Table4-1.png",
    "id": "sp_0001-Table4-1"
  },
  {
    "caption": "Figure 2: t-SNE visualization of the hidden layer activations of a two-layer GraphConv trained on Cora with DFA. Classes forms clear clusters, indicating that a useful intermediary representation is learned. Colors represent different classes.",
    "captionBoundary": {
      "x1": 285.8190002441406,
      "x2": 480.4942626953125,
      "y1": 202.39651489257812,
      "y2": 252.03497314453125
    },
    "figType": "Figure",
    "imageText": [],
    "name": "2",
    "page": 6,
    "regionBoundary": {
      "x1": 302.88,
      "x2": 462.24,
      "y1": 70.56,
      "y2": 191.04
    },
    "renderDpi": 150,
    "renderURL": "//Users/meghamariam/PROJECTS/PROJ1_Dataset/PROJ1_Crossmodal-Traversal/DATASET/pap-seg/fig/sp_0001/sp_0001-Figure2-1.png",
    "id": "sp_0001-Figure2-1"
  },
  {
    "caption": "Figure A.3: Sample renders for every scene of the NeRF-Synthetic dataset, for NeRF and NeRF-Dual trained with DFA.",
    "captionBoundary": {
      "x1": 108.0,
      "x2": 504.00146484375,
      "y1": 614.9515380859375,
      "y2": 631.863037109375
    },
    "figType": "Figure",
    "imageText": [],
    "name": "A.3",
    "page": 21,
    "regionBoundary": {
      "x1": 108.0,
      "x2": 505.44,
      "y1": 156.0,
      "y2": 604.3199999999999
    },
    "renderDpi": 150,
    "renderURL": "//Users/meghamariam/PROJECTS/PROJ1_Dataset/PROJ1_Crossmodal-Traversal/DATASET/pap-seg/fig/sp_0001/sp_0001-FigureA.3-1.png",
    "id": "sp_0001-FigureA.3-1"
  },
  {
    "caption": "Figure A.2: t-SNE visualization of the hidden layer activations of a two-layer GraphConv trained on Cora with a shallow approach, BP, and DFA. The shallow approach does not train the hidden layer and t-SNE fail to extract any information from the randomly initialized layer. DFA and BP visualizations show identical level of separation between clusters.",
    "captionBoundary": {
      "x1": 107.7509994506836,
      "x2": 503.9974365234375,
      "y1": 190.56954956054688,
      "y2": 229.29998779296875
    },
    "figType": "Figure",
    "imageText": [],
    "name": "A.2",
    "page": 17,
    "regionBoundary": {
      "x1": 108.0,
      "x2": 505.44,
      "y1": 70.56,
      "y2": 179.04
    },
    "renderDpi": 150,
    "renderURL": "//Users/meghamariam/PROJECTS/PROJ1_Dataset/PROJ1_Crossmodal-Traversal/DATASET/pap-seg/fig/sp_0001/sp_0001-FigureA.2-1.png",
    "id": "sp_0001-FigureA.2-1"
  },
  {
    "caption": "Table A.4: Shallow baseline for GCNNs on Cora, CiteSeer, and PubMed [65]. Performance is always well below BP and DFA.",
    "captionBoundary": {
      "x1": 107.64099884033203,
      "x2": 504.0042419433594,
      "y1": 246.25350952148438,
      "y2": 263.16497802734375
    },
    "figType": "Table",
    "imageText": [
      "ChebConv",
      "GraphConv",
      "SplineConv",
      "GATConv",
      "DNAConv",
      "Cora",
      "23.3",
      "37.0",
      "39.6",
      "59.4",
      "30.2",
      "CiteSeer",
      "27.4",
      "33.8",
      "30.1",
      "49.8",
      "24.0",
      "PubMed",
      "37.6",
      "44.8",
      "44.2",
      "67.8",
      "42.2"
    ],
    "name": "A.4",
    "page": 17,
    "regionBoundary": {
      "x1": 141.6,
      "x2": 470.4,
      "y1": 276.0,
      "y2": 331.2
    },
    "renderDpi": 150,
    "renderURL": "//Users/meghamariam/PROJECTS/PROJ1_Dataset/PROJ1_Crossmodal-Traversal/DATASET/pap-seg/fig/sp_0001/sp_0001-TableA.4-1.png",
    "id": "sp_0001-TableA.4-1"
  },
  {
    "caption": "Figure A.4: Sample renders for every scene of the LLFF-Real dataset, for NeRF and NeRF-Dual trained with DFA.",
    "captionBoundary": {
      "x1": 108.0,
      "x2": 503.99749755859375,
      "y1": 605.6575927734375,
      "y2": 622.5689697265625
    },
    "figType": "Figure",
    "imageText": [],
    "name": "A.4",
    "page": 22,
    "regionBoundary": {
      "x1": 108.0,
      "x2": 505.44,
      "y1": 165.6,
      "y2": 595.1999999999999
    },
    "renderDpi": 150,
    "renderURL": "//Users/meghamariam/PROJECTS/PROJ1_Dataset/PROJ1_Crossmodal-Traversal/DATASET/pap-seg/fig/sp_0001/sp_0001-FigureA.4-1.png",
    "id": "sp_0001-FigureA.4-1"
  },
  {
    "caption": "Table 5: Best validation perplexity after 20 epochs of a Transformer trained on WikiText-103 (lower is better). The BP and DFA baselines share all hyper-parameters. In Macro the feedback is applied after every transformer layer, implying weight transport at the layer-scale, while in Micro the feedback is applied after every sub-layer. The learning rate of Adam without the learning rate scheduler is 5.10\u22125. With the scheduler, the initial learning rate is 1.10\u22124 and it is multiplied by 0.2 when performance plateaus, with a patience of 1. * score after 22 epochs to let the learning rate scheduler take effect",
    "captionBoundary": {
      "x1": 106.00700378417969,
      "x2": 505.74383544921875,
      "y1": 73.6335220336914,
      "y2": 145.09100341796875
    },
    "figType": "Table",
    "imageText": [
      "Macro",
      "95.0",
      "77.1",
      "55.0",
      "52.0",
      "34.4",
      "29.8Micro",
      "182",
      "166",
      "99.9",
      "93.3*",
      "DFA",
      "BP",
      "Baseline",
      "+",
      "Adam",
      "+",
      "\u03b22",
      "=",
      "0.999",
      "+",
      "LR",
      "schedule",
      "Baseline",
      "+",
      "\u03b22",
      "=",
      "0.999"
    ],
    "name": "5",
    "page": 7,
    "regionBoundary": {
      "x1": 115.67999999999999,
      "x2": 496.32,
      "y1": 157.92,
      "y2": 213.12
    },
    "renderDpi": 150,
    "renderURL": "//Users/meghamariam/PROJECTS/PROJ1_Dataset/PROJ1_Crossmodal-Traversal/DATASET/pap-seg/fig/sp_0001/sp_0001-Table5-1.png",
    "id": "sp_0001-Table5-1"
  },
  {
    "caption": "Figure 1: Comparisons of NeRF-DFA with state-of-the-art methods trained with BP on the most challenging synthetic and real-world scenes. While NeRF-DFA generates render of lower quality, they maintain multi-view consistency and exhibit no geometric artefacts. BP results from [39].",
    "captionBoundary": {
      "x1": 108.0,
      "x2": 505.2474060058594,
      "y1": 307.7645263671875,
      "y2": 335.5849914550781
    },
    "figType": "Figure",
    "imageText": [],
    "name": "1",
    "page": 3,
    "regionBoundary": {
      "x1": 108.0,
      "x2": 505.44,
      "y1": 70.56,
      "y2": 297.12
    },
    "renderDpi": 150,
    "renderURL": "//Users/meghamariam/PROJECTS/PROJ1_Dataset/PROJ1_Crossmodal-Traversal/DATASET/pap-seg/fig/sp_0001/sp_0001-Figure1-1.png",
    "id": "sp_0001-Figure1-1"
  },
  {
    "caption": "Table 1: Peak Signal to Noise Ratio (PSNR, higher is better) of neural view synthesis methods trained with backpropagation against NeRF trained with DFA. Even when trained with DFA, NeRF outperforms two state-of-the-art methods on a synthetic dataset (NeRF-Synthetic), and achieves fair performance on a challenging real world views datasets (LLFF-Real). BP results from [39].",
    "captionBoundary": {
      "x1": 107.69100189208984,
      "x2": 504.27947998046875,
      "y1": 613.091552734375,
      "y2": 651.8209838867188
    },
    "figType": "Table",
    "imageText": [
      "NeRF-Synthetic",
      "26.05",
      "22.26",
      "24.88",
      "31.01",
      "25.41",
      "LLFF-Real",
      "/",
      "22.84",
      "24.13",
      "26.50",
      "20.77",
      "NV",
      "SRN",
      "LLFF",
      "NeRF",
      "BP",
      "BP",
      "BP",
      "BP",
      "DFA"
    ],
    "name": "1",
    "page": 3,
    "regionBoundary": {
      "x1": 183.84,
      "x2": 428.15999999999997,
      "y1": 664.8,
      "y2": 720.0
    },
    "renderDpi": 150,
    "renderURL": "//Users/meghamariam/PROJECTS/PROJ1_Dataset/PROJ1_Crossmodal-Traversal/DATASET/pap-seg/fig/sp_0001/sp_0001-Table1-1.png",
    "id": "sp_0001-Table1-1"
  },
  {
    "caption": "Table A.3: Shallow baseline for recommender system models on the Criteo dataset. Performance is always well below BP and DFA, as expected.",
    "captionBoundary": {
      "x1": 107.69100189208984,
      "x2": 503.9976806640625,
      "y1": 535.3335571289062,
      "y2": 552.2449951171875
    },
    "figType": "Table",
    "imageText": [
      "DeepFM",
      "Deep&Cross",
      "AFN",
      "AUC",
      "0.7920",
      "0.7324",
      "0.7859",
      "Loss",
      "0.4682",
      "0.5010",
      "0.4685"
    ],
    "name": "A.3",
    "page": 16,
    "regionBoundary": {
      "x1": 217.92,
      "x2": 394.08,
      "y1": 564.9599999999999,
      "y2": 610.0799999999999
    },
    "renderDpi": 150,
    "renderURL": "//Users/meghamariam/PROJECTS/PROJ1_Dataset/PROJ1_Crossmodal-Traversal/DATASET/pap-seg/fig/sp_0001/sp_0001-TableA.3-1.png",
    "id": "sp_0001-TableA.3-1"
  },
  {
    "caption": "Figure A.1: Comparisons of Tiny-NeRF trained with BP, DFA, and a shallow approach. Shallow training is insufficient to learn scene geometry. Lego scene from the NeRF synthetic dataset.",
    "captionBoundary": {
      "x1": 108.0,
      "x2": 504.3632507324219,
      "y1": 225.78353881835938,
      "y2": 242.69500732421875
    },
    "figType": "Figure",
    "imageText": [],
    "name": "A.1",
    "page": 16,
    "regionBoundary": {
      "x1": 108.0,
      "x2": 504.0,
      "y1": 72.0,
      "y2": 215.04
    },
    "renderDpi": 150,
    "renderURL": "//Users/meghamariam/PROJECTS/PROJ1_Dataset/PROJ1_Crossmodal-Traversal/DATASET/pap-seg/fig/sp_0001/sp_0001-FigureA.1-1.png",
    "id": "sp_0001-FigureA.1-1"
  },
  {
    "caption": "Table A.5: Per-scene PSNR for NeRF DFA and BP against other state-of-the-art methods on the Nerf-Synthetic and LLFF-Real. DFA performance is fairly homogeneous across each dataset and in line with the differences in other methods.",
    "captionBoundary": {
      "x1": 107.69100189208984,
      "x2": 504.0033264160156,
      "y1": 444.4485168457031,
      "y2": 472.2699890136719
    },
    "figType": "Table",
    "imageText": [
      "LLFF-Real",
      "22.84",
      "24.13",
      "26.50",
      "20.77",
      "Room",
      "27.29",
      "28.42",
      "32.70",
      "24.20",
      "Fern",
      "21.37",
      "22.95",
      "25.17",
      "21.82",
      "Leaves",
      "18.24",
      "19.52",
      "20.92",
      "16.50",
      "Fortress",
      "26.63",
      "29.40",
      "31.16",
      "25.16",
      "Orchids",
      "17.37",
      "18.52",
      "20.36",
      "16.73",
      "Flower",
      "26.63",
      "25.46",
      "27.40",
      "21.55",
      "T-Rex",
      "22.87",
      "24.15",
      "26.80",
      "19.43",
      "Horns",
      "24.33",
      "24.70",
      "27.45",
      "20.75",
      "NeRF-Synthetic",
      "26.05",
      "22.26",
      "24.88",
      "31.01",
      "25.41",
      "Chair",
      "28.33",
      "26.96",
      "28.72",
      "33.00",
      "28.74",
      "Drums",
      "22.58",
      "17.18",
      "21.13",
      "25.01",
      "22.15",
      "Ficus",
      "24.79",
      "20.73",
      "21.79",
      "30.13",
      "25.61",
      "Hotdog",
      "30.71",
      "26.81",
      "31.41",
      "36.18",
      "28.03",
      "Lego",
      "26.08",
      "20.85",
      "24.54",
      "32.54",
      "24.93",
      "Materials",
      "24.22",
      "18.09",
      "20.72",
      "29.62",
      "25.15",
      "Mic",
      "27.78",
      "26.85",
      "27.48",
      "32.91",
      "25.43",
      "Ship",
      "23.93",
      "20.60",
      "23.22",
      "28.65",
      "23.25",
      "NV",
      "SRN",
      "LLFF",
      "NeRF",
      "BP",
      "BP",
      "BP",
      "BP",
      "DFA"
    ],
    "name": "A.5",
    "page": 19,
    "regionBoundary": {
      "x1": 183.84,
      "x2": 428.15999999999997,
      "y1": 484.79999999999995,
      "y2": 720.0
    },
    "renderDpi": 150,
    "renderURL": "//Users/meghamariam/PROJECTS/PROJ1_Dataset/PROJ1_Crossmodal-Traversal/DATASET/pap-seg/fig/sp_0001/sp_0001-TableA.5-1.png",
    "id": "sp_0001-TableA.5-1"
  },
  {
    "caption": "Table 2: AUC (higher is better) and log loss (lower is better) of recommender systems trained on the Criteo dataset [48]. Even in complex heterogeneous architectures, DFA performance is in line with BP. Values in bold indicate DFA AUC within 0.001 from the BP AUC or better.",
    "captionBoundary": {
      "x1": 107.69100189208984,
      "x2": 504.00091552734375,
      "y1": 624.0005493164062,
      "y2": 651.8209838867188
    },
    "figType": "Table",
    "imageText": [
      "AUC",
      "0.7915",
      "0.7954",
      "0.7956",
      "0.8104",
      "0.8009",
      "0.7933",
      "0.7924",
      "Loss",
      "0.4687",
      "0.4610",
      "0.4624",
      "0.4414",
      "0.4502",
      "0.4630",
      "0.4621",
      "FM",
      "DeepFM",
      "Deep&Cross",
      "AFN",
      "BP",
      "DFA",
      "BP",
      "DFA",
      "BP",
      "DFA"
    ],
    "name": "2",
    "page": 4,
    "regionBoundary": {
      "x1": 157.92,
      "x2": 454.08,
      "y1": 664.8,
      "y2": 720.0
    },
    "renderDpi": 150,
    "renderURL": "//Users/meghamariam/PROJECTS/PROJ1_Dataset/PROJ1_Crossmodal-Traversal/DATASET/pap-seg/fig/sp_0001/sp_0001-Table2-1.png",
    "id": "sp_0001-Table2-1"
  },
  {
    "caption": "Table A.2: Alignment cosine similarity (standard deviation in parenthesis) of various graph convolutions architectures as measured on the Cora dataset. These values corroborate that DFA successfully trains all architectures considered.",
    "captionBoundary": {
      "x1": 107.69100189208984,
      "x2": 505.6551818847656,
      "y1": 579.5475463867188,
      "y2": 607.3679809570312
    },
    "figType": "Table",
    "imageText": [
      "ChebConv",
      "GraphConv",
      "SplineConv",
      "GATConv",
      "DNAConv",
      "Alignment",
      "0.87",
      "(0.12)",
      "0.77",
      "(0.25)",
      "0.56",
      "(0.22)",
      "0.63",
      "(0.18)",
      "0.92",
      "(0.30)"
    ],
    "name": "A.2",
    "page": 15,
    "regionBoundary": {
      "x1": 136.79999999999998,
      "x2": 475.2,
      "y1": 620.16,
      "y2": 654.24
    },
    "renderDpi": 150,
    "renderURL": "//Users/meghamariam/PROJECTS/PROJ1_Dataset/PROJ1_Crossmodal-Traversal/DATASET/pap-seg/fig/sp_0001/sp_0001-TableA.2-1.png",
    "id": "sp_0001-TableA.2-1"
  },
  {
    "caption": "Table A.1: Alignment cosine similarity (higher is better, standard deviation in parenthesis) of recommender systems as measured on the Criteo dataset. Learning occurs in both architectures, and high variance may explain the larger performance gap on Deep & Cross compared to other methods.",
    "captionBoundary": {
      "x1": 107.69100189208984,
      "x2": 504.0041198730469,
      "y1": 412.94952392578125,
      "y2": 440.7699890136719
    },
    "figType": "Table",
    "imageText": [
      "Deep",
      "&",
      "Cross",
      "AFN",
      "Alignment",
      "0.40",
      "(0.91)",
      "0.49",
      "(0.08)"
    ],
    "name": "A.1",
    "page": 15,
    "regionBoundary": {
      "x1": 219.84,
      "x2": 392.15999999999997,
      "y1": 453.59999999999997,
      "y2": 487.2
    },
    "renderDpi": 150,
    "renderURL": "//Users/meghamariam/PROJECTS/PROJ1_Dataset/PROJ1_Crossmodal-Traversal/DATASET/pap-seg/fig/sp_0001/sp_0001-TableA.1-1.png",
    "id": "sp_0001-TableA.1-1"
  }
]